dorsa_datetime/__init__.py
dorsa_datetime/datetime_funcs.py
dorsa_datetime-1.0.1.dist-info/LICENSE.txt
dorsa_datetime-1.0.1.dist-info/METADATA
dorsa_datetime-1.0.1.dist-info/WHEEL
dorsa_datetime-1.0.1.dist-info/top_level.txt
dorsa_datetime-1.0.1.dist-info/RECORD
