Metadata-Version: 2.1
Name: dorsa-datetime
Version: 1.0.1
Summary: Find current date and time
Home-page: https://github.com/DORSA-co/modules/tree/main/DORSA_DateTime
Author: Dorsa-co
Author-email: info@dorsa-co.ir
License: Apache License 2.0
Project-URL: Bug Tracker, https://github.com/DORSA-co/modules/tree/main/DORSA_DateTime/issues
Keywords: pypi,dorsa_datetime,tutorial
Classifier: Intended Audience :: Developers
Classifier: Topic :: Software Development :: Documentation
Classifier: License :: OSI Approved :: Apache Software License
Classifier: Programming Language :: Python :: 3
Classifier: Programming Language :: Python :: 3.7
Classifier: Programming Language :: Python :: 3.8
Classifier: Programming Language :: Python :: 3.9
Classifier: Programming Language :: Python :: 3.10
License-File: LICENSE.txt
Requires-Dist: persiantools
